[
  {
    "title": "tensorspace-team/tensorspace",
    "url": "https://github.com/tensorspace-team/tensorspace",
    "lang": "JavaScript"
  },
  {
    "title": "GoogleChromeLabs/squoosh",
    "url": "https://github.com/GoogleChromeLabs/squoosh",
    "lang": "TypeScript"
  },
  {
    "title": "LUX-Core/lux",
    "url": "https://github.com/LUX-Core/lux",
    "lang": "C++"
  },
  {
    "title": "s0md3v/XSStrike",
    "url": "https://github.com/s0md3v/XSStrike",
    "lang": "Python"
  },
  {
    "title": "GoogleChromeLabs/ProjectVisBug",
    "url": "https://github.com/GoogleChromeLabs/ProjectVisBug",
    "lang": "JavaScript"
  },
  {
    "title": "yangchong211/YCBlogs",
    "url": "https://github.com/yangchong211/YCBlogs"
  },
  {
    "title": "maxmcd/webtty",
    "url": "https://github.com/maxmcd/webtty",
    "lang": "Go"
  },
  {
    "title": "scutan90/DeepLearning-500-questions",
    "url": "https://github.com/scutan90/DeepLearning-500-questions",
    "lang": "TeX"
  },
  {
    "title": "nasa/openmct",
    "url": "https://github.com/nasa/openmct",
    "lang": "JavaScript"
  },
  {
    "title": "marian42/wavefunctioncollapse",
    "url": "https://github.com/marian42/wavefunctioncollapse",
    "lang": "C#"
  },
  {
    "title": "tbodt/ish",
    "url": "https://github.com/tbodt/ish",
    "lang": "C"
  },
  {
    "title": "GcsSloop/AndroidNote",
    "url": "https://github.com/GcsSloop/AndroidNote",
    "lang": "Java"
  },
  {
    "title": "google/uis-rnn",
    "url": "https://github.com/google/uis-rnn",
    "lang": "Python"
  },
  {
    "title": "alienzhou/frontend-tech-list",
    "url": "https://github.com/alienzhou/frontend-tech-list"
  },
  {
    "title": "Raathigesh/retoggle",
    "url": "https://github.com/Raathigesh/retoggle",
    "lang": "TypeScript"
  },
  {
    "title": "leonardomso/33-js-concepts",
    "url": "https://github.com/leonardomso/33-js-concepts",
    "lang": "JavaScript"
  },
  {
    "title": "atlassian/react-beautiful-dnd",
    "url": "https://github.com/atlassian/react-beautiful-dnd",
    "lang": "JavaScript"
  },
  {
    "title": "akveo/eva-icons",
    "url": "https://github.com/akveo/eva-icons",
    "lang": "TypeScript"
  },
  {
    "title": "enquirer/enquirer",
    "url": "https://github.com/enquirer/enquirer",
    "lang": "JavaScript"
  },
  {
    "title": "valdrinkoshi/virtual-scroller",
    "url": "https://github.com/valdrinkoshi/virtual-scroller",
    "lang": "JavaScript"
  },
  {
    "title": "ainilili/ratel",
    "url": "https://github.com/ainilili/ratel",
    "lang": "Java"
  },
  {
    "title": "yandexdataschool/nlp_course",
    "url": "https://github.com/yandexdataschool/nlp_course",
    "lang": "JupyterNotebook"
  },
  {
    "title": "antonmedv/fx",
    "url": "https://github.com/antonmedv/fx",
    "lang": "JavaScript"
  },
  {
    "title": "30-seconds/30-seconds-of-code",
    "url": "https://github.com/30-seconds/30-seconds-of-code",
    "lang": "JavaScript"
  },
  {
    "title": "apple/sourcekit-lsp",
    "url": "https://github.com/apple/sourcekit-lsp",
    "lang": "Swift"
  }
]