[
  {
    "title": "bradtraversy/proshop_mern",
    "url": "https://github.com/bradtraversy/proshop_mern",
    "lang": "JavaScript"
  },
  {
    "title": "kentcdodds/advanced-react-patterns",
    "url": "https://github.com/kentcdodds/advanced-react-patterns",
    "lang": "JavaScript"
  },
  {
    "title": "puma/puma",
    "url": "https://github.com/puma/puma",
    "lang": "Ruby"
  },
  {
    "title": "huggingface/datasets",
    "url": "https://github.com/huggingface/datasets",
    "lang": "Python"
  },
  {
    "title": "terraform-aws-modules/terraform-aws-vpc",
    "url": "https://github.com/terraform-aws-modules/terraform-aws-vpc",
    "lang": "HCL"
  },
  {
    "title": "gchq/CyberChef",
    "url": "https://github.com/gchq/CyberChef",
    "lang": "JavaScript"
  },
  {
    "title": "anandpawara/Real_Time_Image_Animation",
    "url": "https://github.com/anandpawara/Real_Time_Image_Animation",
    "lang": "Python"
  },
  {
    "title": "mingrammer/diagrams",
    "url": "https://github.com/mingrammer/diagrams",
    "lang": "Python"
  },
  {
    "title": "TheAlgorithms/Javascript",
    "url": "https://github.com/TheAlgorithms/Javascript",
    "lang": "JavaScript"
  },
  {
    "title": "bellard/quickjs",
    "url": "https://github.com/bellard/quickjs",
    "lang": "C"
  },
  {
    "title": "airbnb/visx",
    "url": "https://github.com/airbnb/visx",
    "lang": "TypeScript"
  },
  {
    "title": "farag2/Windows-10-Sophia-Script",
    "url": "https://github.com/farag2/Windows-10-Sophia-Script",
    "lang": "PowerShell"
  },
  {
    "title": "kentcdodds/react-fundamentals",
    "url": "https://github.com/kentcdodds/react-fundamentals",
    "lang": "JavaScript"
  },
  {
    "title": "crweiner/hacktoberfest-swag-list",
    "url": "https://github.com/crweiner/hacktoberfest-swag-list",
    "lang": "Ruby"
  },
  {
    "title": "microsoft/PowerToys",
    "url": "https://github.com/microsoft/PowerToys",
    "lang": "C++"
  },
  {
    "title": "NVlabs/imaginaire",
    "url": "https://github.com/NVlabs/imaginaire",
    "lang": "Python"
  },
  {
    "title": "gdtool/zhaopp",
    "url": "https://github.com/gdtool/zhaopp",
    "lang": "JavaScript"
  },
  {
    "title": "jeremylong/DependencyCheck",
    "url": "https://github.com/jeremylong/DependencyCheck",
    "lang": "Java"
  },
  {
    "title": "datastacktv/data-engineer-roadmap",
    "url": "https://github.com/datastacktv/data-engineer-roadmap"
  },
  {
    "title": "OpenMined/PySyft",
    "url": "https://github.com/OpenMined/PySyft",
    "lang": "Python"
  },
  {
    "title": "kentcdodds/advanced-react-hooks",
    "url": "https://github.com/kentcdodds/advanced-react-hooks",
    "lang": "JavaScript"
  },
  {
    "title": "kentcdodds/react-performance",
    "url": "https://github.com/kentcdodds/react-performance",
    "lang": "JavaScript"
  },
  {
    "title": "akshitagit/CPP",
    "url": "https://github.com/akshitagit/CPP",
    "lang": "C++"
  },
  {
    "title": "cypress-io/cypress-realworld-app",
    "url": "https://github.com/cypress-io/cypress-realworld-app",
    "lang": "TypeScript"
  },
  {
    "title": "kentcdodds/react-suspense",
    "url": "https://github.com/kentcdodds/react-suspense",
    "lang": "JavaScript"
  }
]