[
  {
    "title": "donnemartin/system-design-primer",
    "url": "https://github.com/donnemartin/system-design-primer",
    "lang": "Python"
  },
  {
    "title": "Fmstrat/winapps",
    "url": "https://github.com/Fmstrat/winapps",
    "lang": "Shell"
  },
  {
    "title": "cjph8914/2020_benfords",
    "url": "https://github.com/cjph8914/2020_benfords",
    "lang": "JupyterNotebook"
  },
  {
    "title": "chatwoot/chatwoot",
    "url": "https://github.com/chatwoot/chatwoot",
    "lang": "Ruby"
  },
  {
    "title": "arendst/Tasmota",
    "url": "https://github.com/arendst/Tasmota",
    "lang": "C"
  },
  {
    "title": "rileytestut/AltStore",
    "url": "https://github.com/rileytestut/AltStore",
    "lang": "Swift"
  },
  {
    "title": "gao-sun/eul",
    "url": "https://github.com/gao-sun/eul",
    "lang": "Swift"
  },
  {
    "title": "geekxh/hello-algorithm",
    "url": "https://github.com/geekxh/hello-algorithm",
    "lang": "Java"
  },
  {
    "title": "RayWangQvQ/BiliBiliTool",
    "url": "https://github.com/RayWangQvQ/BiliBiliTool",
    "lang": "C#"
  },
  {
    "title": "Marak/faker.js",
    "url": "https://github.com/Marak/faker.js",
    "lang": "JavaScript"
  },
  {
    "title": "PavelDoGreat/WebGL-Fluid-Simulation",
    "url": "https://github.com/PavelDoGreat/WebGL-Fluid-Simulation",
    "lang": "JavaScript"
  },
  {
    "title": "appbrewery/100-days-of-python",
    "url": "https://github.com/appbrewery/100-days-of-python"
  },
  {
    "title": "yogeshojha/rengine",
    "url": "https://github.com/yogeshojha/rengine",
    "lang": "JavaScript"
  },
  {
    "title": "Atcold/pytorch-Deep-Learning",
    "url": "https://github.com/Atcold/pytorch-Deep-Learning",
    "lang": "JupyterNotebook"
  },
  {
    "title": "firstcontributions/first-contributions",
    "url": "https://github.com/firstcontributions/first-contributions"
  },
  {
    "title": "newbee-ltd/newbee-mall-vue3-app",
    "url": "https://github.com/newbee-ltd/newbee-mall-vue3-app",
    "lang": "JavaScript"
  },
  {
    "title": "facebookresearch/pifuhd",
    "url": "https://github.com/facebookresearch/pifuhd",
    "lang": "Python"
  },
  {
    "title": "sorrycc/awesome-javascript",
    "url": "https://github.com/sorrycc/awesome-javascript"
  },
  {
    "title": "gordicaleksa/pytorch-original-transformer",
    "url": "https://github.com/gordicaleksa/pytorch-original-transformer",
    "lang": "Python"
  },
  {
    "title": "lightspin-tech/red-kube",
    "url": "https://github.com/lightspin-tech/red-kube"
  },
  {
    "title": "thenewboston-developers/Website",
    "url": "https://github.com/thenewboston-developers/Website",
    "lang": "TypeScript"
  },
  {
    "title": "michalsnik/aos",
    "url": "https://github.com/michalsnik/aos",
    "lang": "JavaScript"
  },
  {
    "title": "vlang/v",
    "url": "https://github.com/vlang/v",
    "lang": "V"
  },
  {
    "title": "scarsty/kys-cpp",
    "url": "https://github.com/scarsty/kys-cpp",
    "lang": "C++"
  },
  {
    "title": "allenai/allennlp",
    "url": "https://github.com/allenai/allennlp",
    "lang": "Python"
  }
]