[
  {
    "title": "bytedance/btrace",
    "url": "https://github.com/bytedance/btrace",
    "lang": "Kotlin"
  },
  {
    "title": "sindresorhus/awesome",
    "url": "https://github.com/sindresorhus/awesome"
  },
  {
    "title": "google/log4jscanner",
    "url": "https://github.com/google/log4jscanner",
    "lang": "Go"
  },
  {
    "title": "DataTalksClub/data-engineering-zoomcamp",
    "url": "https://github.com/DataTalksClub/data-engineering-zoomcamp"
  },
  {
    "title": "PaddlePaddle/PaddleDetection",
    "url": "https://github.com/PaddlePaddle/PaddleDetection",
    "lang": "Python"
  },
  {
    "title": "papers-we-love/papers-we-love",
    "url": "https://github.com/papers-we-love/papers-we-love",
    "lang": "Shell"
  },
  {
    "title": "google/python-fire",
    "url": "https://github.com/google/python-fire",
    "lang": "Python"
  },
  {
    "title": "donnemartin/system-design-primer",
    "url": "https://github.com/donnemartin/system-design-primer",
    "lang": "Python"
  },
  {
    "title": "youngyangyang04/leetcode-master",
    "url": "https://github.com/youngyangyang04/leetcode-master"
  },
  {
    "title": "ja-netfilter/ja-netfilter",
    "url": "https://github.com/ja-netfilter/ja-netfilter",
    "lang": "Java"
  },
  {
    "title": "angular/angular",
    "url": "https://github.com/angular/angular",
    "lang": "TypeScript"
  },
  {
    "title": "MicrosoftLearning/AZ-204-DevelopingSolutionsforMicrosoftAzure",
    "url": "https://github.com/MicrosoftLearning/AZ-204-DevelopingSolutionsforMicrosoftAzure",
    "lang": "C#"
  },
  {
    "title": "dfir-iris/iris-web",
    "url": "https://github.com/dfir-iris/iris-web",
    "lang": "JavaScript"
  },
  {
    "title": "CleverRaven/Cataclysm-DDA",
    "url": "https://github.com/CleverRaven/Cataclysm-DDA",
    "lang": "C++"
  },
  {
    "title": "ZLMediaKit/ZLMediaKit",
    "url": "https://github.com/ZLMediaKit/ZLMediaKit",
    "lang": "C++"
  },
  {
    "title": "element-plus/element-plus",
    "url": "https://github.com/element-plus/element-plus",
    "lang": "Vue"
  },
  {
    "title": "Mas0nShi/typoraCracker",
    "url": "https://github.com/Mas0nShi/typoraCracker",
    "lang": "Python"
  },
  {
    "title": "gatsbyjs/gatsby",
    "url": "https://github.com/gatsbyjs/gatsby",
    "lang": "JavaScript"
  },
  {
    "title": "google/gvisor",
    "url": "https://github.com/google/gvisor",
    "lang": "Go"
  },
  {
    "title": "facebook/react-native",
    "url": "https://github.com/facebook/react-native",
    "lang": "JavaScript"
  },
  {
    "title": "hibiken/asynq",
    "url": "https://github.com/hibiken/asynq",
    "lang": "Go"
  },
  {
    "title": "alibaba/formily",
    "url": "https://github.com/alibaba/formily",
    "lang": "TypeScript"
  },
  {
    "title": "skyline-emu/skyline",
    "url": "https://github.com/skyline-emu/skyline",
    "lang": "C++"
  },
  {
    "title": "vnpy/vnpy",
    "url": "https://github.com/vnpy/vnpy",
    "lang": "Python"
  }
]