[
  {
    "title": "cloudwego/kitex",
    "url": "https://github.com/cloudwego/kitex",
    "lang": "Go"
  },
  {
    "title": "dromara/Sa-Token",
    "url": "https://github.com/dromara/Sa-Token",
    "lang": "Java"
  },
  {
    "title": "microsoft/terminal",
    "url": "https://github.com/microsoft/terminal",
    "lang": "C++"
  },
  {
    "title": "facebook/folly",
    "url": "https://github.com/facebook/folly",
    "lang": "C++"
  },
  {
    "title": "grpc/grpc",
    "url": "https://github.com/grpc/grpc",
    "lang": "C++"
  },
  {
    "title": "aws-amplify/amplify-js",
    "url": "https://github.com/aws-amplify/amplify-js",
    "lang": "TypeScript"
  },
  {
    "title": "microsoft/IoT-For-Beginners",
    "url": "https://github.com/microsoft/IoT-For-Beginners",
    "lang": "C++"
  },
  {
    "title": "prathyvsh/pl-catalog",
    "url": "https://github.com/prathyvsh/pl-catalog"
  },
  {
    "title": "AstraZeneca/awesome-explainable-graph-reasoning",
    "url": "https://github.com/AstraZeneca/awesome-explainable-graph-reasoning"
  },
  {
    "title": "typesense/typesense",
    "url": "https://github.com/typesense/typesense",
    "lang": "C++"
  },
  {
    "title": "cloudwego/netpoll",
    "url": "https://github.com/cloudwego/netpoll",
    "lang": "Go"
  },
  {
    "title": "eugeneyan/applied-ml",
    "url": "https://github.com/eugeneyan/applied-ml"
  },
  {
    "title": "cdr/code-server",
    "url": "https://github.com/cdr/code-server",
    "lang": "TypeScript"
  },
  {
    "title": "kon9chunkit/GitHub-Chinese-Top-Charts",
    "url": "https://github.com/kon9chunkit/GitHub-Chinese-Top-Charts",
    "lang": "Java"
  },
  {
    "title": "jaywcjlove/awesome-mac",
    "url": "https://github.com/jaywcjlove/awesome-mac",
    "lang": "JavaScript"
  },
  {
    "title": "opensearch-project/OpenSearch",
    "url": "https://github.com/opensearch-project/OpenSearch",
    "lang": "Java"
  },
  {
    "title": "bndw/wifi-card",
    "url": "https://github.com/bndw/wifi-card",
    "lang": "JavaScript"
  },
  {
    "title": "uzh-rpg/rpg_svo_pro_open",
    "url": "https://github.com/uzh-rpg/rpg_svo_pro_open",
    "lang": "C++"
  },
  {
    "title": "smiek2221/scripts",
    "url": "https://github.com/smiek2221/scripts",
    "lang": "JavaScript"
  },
  {
    "title": "Aaron-lv/sync",
    "url": "https://github.com/Aaron-lv/sync"
  },
  {
    "title": "Jack-Cherish/Machine-Learning",
    "url": "https://github.com/Jack-Cherish/Machine-Learning",
    "lang": "Python"
  },
  {
    "title": "Sangwan5688/BlackHole",
    "url": "https://github.com/Sangwan5688/BlackHole",
    "lang": "Dart"
  },
  {
    "title": "donnemartin/system-design-primer",
    "url": "https://github.com/donnemartin/system-design-primer",
    "lang": "Python"
  },
  {
    "title": "Tencent/TNN",
    "url": "https://github.com/Tencent/TNN",
    "lang": "C++"
  },
  {
    "title": "diekmann/wasm-fizzbuzz",
    "url": "https://github.com/diekmann/wasm-fizzbuzz",
    "lang": "C++"
  }
]