[
  {
    "title": "microsoft/wslg",
    "url": "https://github.com/microsoft/wslg",
    "lang": "C++"
  },
  {
    "title": "rammcodes/Dopefolio",
    "url": "https://github.com/rammcodes/Dopefolio",
    "lang": "HTML"
  },
  {
    "title": "TaKO8Ki/gobang",
    "url": "https://github.com/TaKO8Ki/gobang",
    "lang": "Rust"
  },
  {
    "title": "MoH-Malaysia/covid19-public",
    "url": "https://github.com/MoH-Malaysia/covid19-public"
  },
  {
    "title": "exiled-apes/candy-machine-mint",
    "url": "https://github.com/exiled-apes/candy-machine-mint",
    "lang": "TypeScript"
  },
  {
    "title": "smartcontractkit/full-blockchain-solidity-course-py",
    "url": "https://github.com/smartcontractkit/full-blockchain-solidity-course-py"
  },
  {
    "title": "graviraja/MLOps-Basics",
    "url": "https://github.com/graviraja/MLOps-Basics",
    "lang": "JupyterNotebook"
  },
  {
    "title": "supabase/supabase",
    "url": "https://github.com/supabase/supabase",
    "lang": "TypeScript"
  },
  {
    "title": "cloudwego/netpoll",
    "url": "https://github.com/cloudwego/netpoll",
    "lang": "Go"
  },
  {
    "title": "godotengine/godot",
    "url": "https://github.com/godotengine/godot",
    "lang": "C++"
  },
  {
    "title": "ChoiceCoin/Voting",
    "url": "https://github.com/ChoiceCoin/Voting",
    "lang": "Python"
  },
  {
    "title": "Saul-Mirone/milkdown",
    "url": "https://github.com/Saul-Mirone/milkdown",
    "lang": "TypeScript"
  },
  {
    "title": "CyberPunkMetalHead/binance-trading-bot-new-coins",
    "url": "https://github.com/CyberPunkMetalHead/binance-trading-bot-new-coins",
    "lang": "Python"
  },
  {
    "title": "AshishJangra27/Skill-India-AI-ML-Scholarship",
    "url": "https://github.com/AshishJangra27/Skill-India-AI-ML-Scholarship",
    "lang": "JupyterNotebook"
  },
  {
    "title": "ryanmcdermott/clean-code-javascript",
    "url": "https://github.com/ryanmcdermott/clean-code-javascript",
    "lang": "JavaScript"
  },
  {
    "title": "DataDog/go-profiler-notes",
    "url": "https://github.com/DataDog/go-profiler-notes",
    "lang": "JupyterNotebook"
  },
  {
    "title": "spulec/moto",
    "url": "https://github.com/spulec/moto",
    "lang": "Python"
  },
  {
    "title": "coolsnowwolf/lede",
    "url": "https://github.com/coolsnowwolf/lede",
    "lang": "C"
  },
  {
    "title": "flutter/flutter",
    "url": "https://github.com/flutter/flutter",
    "lang": "Dart"
  },
  {
    "title": "microsoft/ML-For-Beginners",
    "url": "https://github.com/microsoft/ML-For-Beginners",
    "lang": "JupyterNotebook"
  },
  {
    "title": "theme-next/hexo-theme-next",
    "url": "https://github.com/theme-next/hexo-theme-next",
    "lang": "Stylus"
  },
  {
    "title": "Genymobile/scrcpy",
    "url": "https://github.com/Genymobile/scrcpy",
    "lang": "C"
  },
  {
    "title": "diego3g/umbriel",
    "url": "https://github.com/diego3g/umbriel",
    "lang": "TypeScript"
  },
  {
    "title": "bnjbvr/rouille",
    "url": "https://github.com/bnjbvr/rouille",
    "lang": "Rust"
  },
  {
    "title": "HashLips/generative-art-node",
    "url": "https://github.com/HashLips/generative-art-node",
    "lang": "JavaScript"
  }
]