[
  {
    "title": "medusajs/medusa",
    "url": "https://github.com/medusajs/medusa",
    "lang": "JavaScript"
  },
  {
    "title": "ant-design/ant-design",
    "url": "https://github.com/ant-design/ant-design",
    "lang": "TypeScript"
  },
  {
    "title": "flutter/flutter",
    "url": "https://github.com/flutter/flutter",
    "lang": "Dart"
  },
  {
    "title": "jeecgboot/jeecg-boot",
    "url": "https://github.com/jeecgboot/jeecg-boot",
    "lang": "Java"
  },
  {
    "title": "3b1b/videos",
    "url": "https://github.com/3b1b/videos",
    "lang": "Python"
  },
  {
    "title": "jpetazzo/ampernetacle",
    "url": "https://github.com/jpetazzo/ampernetacle",
    "lang": "HCL"
  },
  {
    "title": "sindresorhus/awesome",
    "url": "https://github.com/sindresorhus/awesome"
  },
  {
    "title": "imDazui/Tvlist-awesome-m3u-m3u8",
    "url": "https://github.com/imDazui/Tvlist-awesome-m3u-m3u8"
  },
  {
    "title": "saifulcoder/laravel-whatsapp-server",
    "url": "https://github.com/saifulcoder/laravel-whatsapp-server",
    "lang": "PHP"
  },
  {
    "title": "Asabeneh/30-Days-Of-JavaScript",
    "url": "https://github.com/Asabeneh/30-Days-Of-JavaScript",
    "lang": "JavaScript"
  },
  {
    "title": "LaunchX-InnovaccionVirtual/onboarding-github-launchx",
    "url": "https://github.com/LaunchX-InnovaccionVirtual/onboarding-github-launchx"
  },
  {
    "title": "vbenjs/vue-vben-admin",
    "url": "https://github.com/vbenjs/vue-vben-admin",
    "lang": "Vue"
  },
  {
    "title": "alibaba/DataX",
    "url": "https://github.com/alibaba/DataX",
    "lang": "Java"
  },
  {
    "title": "elastic/beats",
    "url": "https://github.com/elastic/beats",
    "lang": "Go"
  },
  {
    "title": "danistefanovic/build-your-own-x",
    "url": "https://github.com/danistefanovic/build-your-own-x"
  },
  {
    "title": "zadam/trilium",
    "url": "https://github.com/zadam/trilium",
    "lang": "JavaScript"
  },
  {
    "title": "DaveGamble/cJSON",
    "url": "https://github.com/DaveGamble/cJSON",
    "lang": "C"
  },
  {
    "title": "3b1b/manim",
    "url": "https://github.com/3b1b/manim",
    "lang": "Python"
  },
  {
    "title": "goldbergyoni/nodebestpractices",
    "url": "https://github.com/goldbergyoni/nodebestpractices",
    "lang": "JavaScript"
  },
  {
    "title": "jerry3747/taobao_seckill",
    "url": "https://github.com/jerry3747/taobao_seckill",
    "lang": "Python"
  },
  {
    "title": "gyroflow/gyroflow",
    "url": "https://github.com/gyroflow/gyroflow",
    "lang": "Rust"
  },
  {
    "title": "ossu/computer-science",
    "url": "https://github.com/ossu/computer-science"
  },
  {
    "title": "mit-dci/opencbdc-tx",
    "url": "https://github.com/mit-dci/opencbdc-tx",
    "lang": "C++"
  },
  {
    "title": "apache/rocketmq",
    "url": "https://github.com/apache/rocketmq",
    "lang": "Java"
  },
  {
    "title": "vuejs/devtools",
    "url": "https://github.com/vuejs/devtools",
    "lang": "TypeScript"
  }
]